setup.py
brynq_sdk_visma_lon_hr/__init__.py
brynq_sdk_visma_lon_hr/absence.py
brynq_sdk_visma_lon_hr/absence_group.py
brynq_sdk_visma_lon_hr/absence_type.py
brynq_sdk_visma_lon_hr/classification.py
brynq_sdk_visma_lon_hr/compensation_and_benefit.py
brynq_sdk_visma_lon_hr/content_type.py
brynq_sdk_visma_lon_hr/course.py
brynq_sdk_visma_lon_hr/course_calendar.py
brynq_sdk_visma_lon_hr/course_supplier.py
brynq_sdk_visma_lon_hr/customer.py
brynq_sdk_visma_lon_hr/employee.py
brynq_sdk_visma_lon_hr/employee_qualification.py
brynq_sdk_visma_lon_hr/employer.py
brynq_sdk_visma_lon_hr/employment.py
brynq_sdk_visma_lon_hr/employment_classification.py
brynq_sdk_visma_lon_hr/organization.py
brynq_sdk_visma_lon_hr/organizational_unit.py
brynq_sdk_visma_lon_hr/pay_type.py
brynq_sdk_visma_lon_hr/payment_condition_classification.py
brynq_sdk_visma_lon_hr/payroll.py
brynq_sdk_visma_lon_hr/phone_number.py
brynq_sdk_visma_lon_hr/posted_accounting.py
brynq_sdk_visma_lon_hr/processed_absence.py
brynq_sdk_visma_lon_hr/processed_absence_group.py
brynq_sdk_visma_lon_hr/salary.py
brynq_sdk_visma_lon_hr/salary_comment.py
brynq_sdk_visma_lon_hr/tables.py
brynq_sdk_visma_lon_hr/tax_card.py
brynq_sdk_visma_lon_hr/utils.py
brynq_sdk_visma_lon_hr/visma.py
brynq_sdk_visma_lon_hr/work_calendar.py
brynq_sdk_visma_lon_hr.egg-info/PKG-INFO
brynq_sdk_visma_lon_hr.egg-info/SOURCES.txt
brynq_sdk_visma_lon_hr.egg-info/dependency_links.txt
brynq_sdk_visma_lon_hr.egg-info/not-zip-safe
brynq_sdk_visma_lon_hr.egg-info/requires.txt
brynq_sdk_visma_lon_hr.egg-info/top_level.txt
brynq_sdk_visma_lon_hr/legacy/get_data.py
brynq_sdk_visma_lon_hr/schemas/__init__.py
brynq_sdk_visma_lon_hr/schemas/absence.py
brynq_sdk_visma_lon_hr/schemas/absence_group.py
brynq_sdk_visma_lon_hr/schemas/absence_type.py
brynq_sdk_visma_lon_hr/schemas/classification.py
brynq_sdk_visma_lon_hr/schemas/compensation_and_benefit.py
brynq_sdk_visma_lon_hr/schemas/content_type.py
brynq_sdk_visma_lon_hr/schemas/course.py
brynq_sdk_visma_lon_hr/schemas/course_calendar.py
brynq_sdk_visma_lon_hr/schemas/course_supplier.py
brynq_sdk_visma_lon_hr/schemas/customer.py
brynq_sdk_visma_lon_hr/schemas/employee.py
brynq_sdk_visma_lon_hr/schemas/employee_qualification.py
brynq_sdk_visma_lon_hr/schemas/employer.py
