Metadata-Version: 1.0
Name: brynq-sdk-visma-lon-hr
Version: 3.1.0
Summary: Visma Lon & HR wrapper from BrynQ
Home-page: UNKNOWN
Author: BrynQ
Author-email: support@brynq.com
License: BrynQ License
Platform: UNKNOWN
